elasticsearch_dsl/__init__.py
elasticsearch_dsl/aggs.py
elasticsearch_dsl/analysis.py
elasticsearch_dsl/async_connections.py
elasticsearch_dsl/connections.py
elasticsearch_dsl/document.py
elasticsearch_dsl/document_base.py
elasticsearch_dsl/exceptions.py
elasticsearch_dsl/faceted_search.py
elasticsearch_dsl/faceted_search_base.py
elasticsearch_dsl/field.py
elasticsearch_dsl/function.py
elasticsearch_dsl/index.py
elasticsearch_dsl/index_base.py
elasticsearch_dsl/mapping.py
elasticsearch_dsl/mapping_base.py
elasticsearch_dsl/py.typed
elasticsearch_dsl/query.py
elasticsearch_dsl/search.py
elasticsearch_dsl/search_base.py
elasticsearch_dsl/serializer.py
elasticsearch_dsl/types.py
elasticsearch_dsl/update_by_query.py
elasticsearch_dsl/update_by_query_base.py
elasticsearch_dsl/utils.py
elasticsearch_dsl/wrappers.py
elasticsearch_dsl/_async/__init__.py
elasticsearch_dsl/_async/document.py
elasticsearch_dsl/_async/faceted_search.py
elasticsearch_dsl/_async/index.py
elasticsearch_dsl/_async/mapping.py
elasticsearch_dsl/_async/search.py
elasticsearch_dsl/_async/update_by_query.py
elasticsearch_dsl/_sync/__init__.py
elasticsearch_dsl/_sync/document.py
elasticsearch_dsl/_sync/faceted_search.py
elasticsearch_dsl/_sync/index.py
elasticsearch_dsl/_sync/mapping.py
elasticsearch_dsl/_sync/search.py
elasticsearch_dsl/_sync/update_by_query.py
elasticsearch_dsl/response/__init__.py
elasticsearch_dsl/response/aggs.py
elasticsearch_dsl/response/hit.py
elasticsearch_dsl-8.17.1.dist-info/AUTHORS
elasticsearch_dsl-8.17.1.dist-info/LICENSE
elasticsearch_dsl-8.17.1.dist-info/METADATA
elasticsearch_dsl-8.17.1.dist-info/WHEEL
elasticsearch_dsl-8.17.1.dist-info/top_level.txt
elasticsearch_dsl-8.17.1.dist-info/RECORD
