Metadata-Version: 2.1
Name: elasticsearch-dsl
Version: 8.17.1
Summary: Python client for Elasticsearch
Home-page: https://github.com/elasticsearch/elasticsearch-dsl-py
Author: Elastic Client Library Maintainers
Author-email: client-libs@elastic.co
License: Apache-2.0
Classifier: Development Status :: 4 - Beta
Classifier: License :: OSI Approved :: Apache Software License
Classifier: Intended Audience :: Developers
Classifier: Operating System :: OS Independent
Classifier: Programming Language :: Python
Classifier: Programming Language :: Python :: 3
Classifier: Programming Language :: Python :: 3 :: Only
Classifier: Programming Language :: Python :: 3.8
Classifier: Programming Language :: Python :: 3.9
Classifier: Programming Language :: Python :: 3.10
Classifier: Programming Language :: Python :: 3.11
Classifier: Programming Language :: Python :: 3.12
Classifier: Programming Language :: Python :: 3.13
Classifier: Programming Language :: Python :: Implementation :: CPython
Classifier: Programming Language :: Python :: Implementation :: PyPy
Requires-Python: >=3.8
License-File: LICENSE
License-File: AUTHORS
Requires-Dist: python-dateutil
Requires-Dist: typing-extensions
Requires-Dist: elasticsearch<9.0.0,>=8.0.0
Requires-Dist: elastic-transport<9.0.0,>=8.0.0
Provides-Extra: async
Requires-Dist: elasticsearch[async]<9.0.0,>=8.0.0; extra == "async"
Provides-Extra: develop
Requires-Dist: elasticsearch[async]; extra == "develop"
Requires-Dist: unasync; extra == "develop"
Requires-Dist: jinja2; extra == "develop"
Requires-Dist: pytest; extra == "develop"
Requires-Dist: pytest-cov; extra == "develop"
Requires-Dist: pytest-mock; extra == "develop"
Requires-Dist: pytest-asyncio; extra == "develop"
Requires-Dist: pytz; extra == "develop"
Requires-Dist: coverage; extra == "develop"
Requires-Dist: nltk; extra == "develop"
Requires-Dist: sentence_transformers; extra == "develop"
Requires-Dist: tqdm; extra == "develop"
Requires-Dist: sphinx>2; extra == "develop"
Requires-Dist: sphinx-rtd-theme>0.5; extra == "develop"
Requires-Dist: mypy; extra == "develop"
Requires-Dist: pyright; extra == "develop"
Requires-Dist: types-python-dateutil; extra == "develop"
Requires-Dist: types-pytz; extra == "develop"
Requires-Dist: types-tqdm; extra == "develop"
